{
    "facility": {
        "type": "laboratory",
        "lab_id": "f780441f60a30a86b752e00adb66f107",
        "research_infrastructure_name": "CNRS-INSU-MESRI",
        "name": "TECMOD-France",
        "general_description": "\n\nTECMOD-F (French Tectonic Modeling network) is a national collaborative network involving French laboratories developing research projects integrating analog or experimental modeling techniques dedicated to the study of geological processes where tectonics plays a significant role. All the scales of time and space are investigated, including long term orogenic processes to morphogenetic processes, until short term seismic deformation, from the deformation at the scale of the lithosphere up to the fracturation and faulting at the scale of a massif or a rock sample. To date, 9 laboratories are connected to the network; Géosciences Rennes, Géosciences Montpellier, GéoSystèmes Lille, GéoAzur, GéophyLab Nantes, Géosciences Environnement Toulouse, Géosciences et environnement Cergy, Magma et Volcan Clermont-Ferrand, FAST Orsay. The National Center for Scientific Research (CNRS-INSU) and the Ministry of Higher Education, Research and Innovation (MESRI) insures the legal coordination within the consortium. List of the main institutes and partners of the TECTMOD-F network: National Institute for Earth Sciences and Astronomy (CNRS-INSU), The French Geological Survey (BRGM), The National Research Institute for Sustainable Development (IRD), French and international private companies such as : TOTAL, Schlumberger, IFP Energie Nouvelle, REPSOL, …\nThe internal coordination of the consortium is insured in a collective way and managed by the representatives of laboratories and partners: Géosciences Rennes (B. Guillaume), Géosciences Montpellier (S. Dominguez), GéoSystèmes Lilles (B. Vendeville), GéoAzur (A. Chemenda), GéophyLab Nantes (R. Mourgues), Géosciences Environnement Toulouse (S. Bonnet), Géosciences et environnement Cergy (P. Souloumiac), Magma et Volcan Clermont-Ferrand (O. Roche), FAST Orsay (A. Davaille).",
        "address": {
            "street_with_number": "University of Montpellier - Campus Triolet - Place E. Bataillon - cc60",
            "postal_code": "34095",
            "city": "Montpellier",
            "country": "France"
        },
        "gps": {
            "gps_lat": "43.632°N",
            "gps_lon": "3.867°E"
        },
        "website": "http://tecmodweb.free.fr/TecMOD_France/Accueil_English.html",
        "contact_person": {
            "first_name": "Stephane",
            "family_name": "Dominguez",
            "identifier": {
                "id_type": "",
                "id_value": "ORCID: 0000-0001-8218-7144, ResearcherID: C-5240-2011"
            },
            "email": "",
            "affiliation": {
                "legal_name": "CNRS-Université de Montpellier,  France",
                "identifier": {
                    "id_type": "",
                    "id_value": ""
                },
                "address": {
                    "street_with_number": "",
                    "postal_code": "",
                    "city": "",
                    "country": ""
                }
            }
        },
        "lab_services": {
            "research_field": "Analogue modelling of geologic processes",
            "EPOS_subdomain": [
                "Analogue models on tectonic processes"
            ],
            "equipment": [
                {
                    "equipment_type": "Apparatus",
                    "equipment_name": "",
                    "equipment_brand": "",
                    "equipment_contact_person": "",
                    "email_equipment_contact_person": "",
                    "equipment_website": "",
                    "equipment_specifics_and_comments": "",
                    "equipment_quantity": "",
                    "references": ""
                },
                {
                    "equipment_type": "",
                    "equipment_group": "TAB3D Passive margin simulator",
                    "equipment_name": "Passive margin simulator",
                    "equipment_brand": "Lab-made prototype",
                    "equipment_contact_person": "Benjamin GUILLAUME",
                    "email_equipment_contact_person": "benjamin.guillaume@univ-rennes1.fr",
                    "equipment_website": "GRmodel - CNRS-Rennes 1 University, France",
                    "equipment_specifics_and_comments": "",
                    "equipment_quantity": 1.0,
                    "references": ""
                },
                {
                    "equipment_type": "Apparatus Thermomechanics apparatus",
                    "equipment_group": "THERMOMEC",
                    "equipment_name": "Machine thermique",
                    "equipment_brand": "Lab-made prototype",
                    "equipment_contact_person": "Benjamin GUILLAUME",
                    "email_equipment_contact_person": "benjamin.guillaume@univ-rennes1.fr",
                    "equipment_website": "GRmodel - CNRS-Rennes 1 University, France",
                    "equipment_specifics_and_comments": "",
                    "equipment_quantity": 1.0,
                    "references": ""
                },
                {
                    "equipment_type": "Apparatus",
                    "equipment_group": "OVERPRESS",
                    "equipment_name": "Pression fluide",
                    "equipment_brand": "Lab-made prototype",
                    "equipment_contact_person": "Benjamin GUILLAUME",
                    "email_equipment_contact_person": "benjamin.guillaume@univ-rennes1.fr",
                    "equipment_website": "GRmodel - CNRS-Rennes 1 University, France",
                    "equipment_specifics_and_comments": "",
                    "equipment_quantity": 1.0,
                    "references": ""
                },
                {
                    "equipment_type": "Apparatus Shear box",
                    "equipment_group": "SHEARBOX",
                    "equipment_name": "Machine à cisaillement",
                    "equipment_brand": "Lab-made prototype",
                    "equipment_contact_person": "Benjamin GUILLAUME",
                    "email_equipment_contact_person": "benjamin.guillaume@univ-rennes1.fr",
                    "equipment_website": "GRmodel - CNRS-Rennes 1 University, France",
                    "equipment_specifics_and_comments": "",
                    "equipment_quantity": 1.0,
                    "references": ""
                },
                {
                    "equipment_type": "Apparatus River system simulator",
                    "equipment_group": "MINIRIVER",
                    "equipment_name": "Chenal incision simulator",
                    "equipment_brand": "Lab-made prototype",
                    "equipment_contact_person": "Benjamin GUILLAUME",
                    "email_equipment_contact_person": "benjamin.guillaume@univ-rennes1.fr",
                    "equipment_website": "GRmodel - CNRS-Rennes 1 University, France",
                    "equipment_specifics_and_comments": "",
                    "equipment_quantity": 1.0,
                    "references": ""
                },
                {
                    "equipment_type": "Apparatus Subduction box",
                    "equipment_group": "SUBFLOW3D",
                    "equipment_name": "Subduction simulator",
                    "equipment_brand": "Lab-made prototype",
                    "equipment_contact_person": "Benjamin GUILLAUME",
                    "email_equipment_contact_person": "benjamin.guillaume@univ-rennes1.fr",
                    "equipment_website": "GRmodel - CNRS-Rennes 1 University, France",
                    "equipment_specifics_and_comments": "",
                    "equipment_quantity": 1.0,
                    "references": ""
                },
                {
                    "equipment_type": "Software",
                    "equipment_name": "",
                    "equipment_brand": "",
                    "equipment_contact_person": "Benjamin GUILLAUME",
                    "email_equipment_contact_person": "benjamin.guillaume@univ-rennes1.fr",
                    "equipment_website": "GRmodel - CNRS-Rennes 1 University, France",
                    "equipment_specifics_and_comments": "",
                    "equipment_quantity": "",
                    "references": ""
                },
                {
                    "equipment_type": "",
                    "equipment_name": "",
                    "equipment_brand": "",
                    "equipment_contact_person": "",
                    "email_equipment_contact_person": "",
                    "equipment_website": "",
                    "equipment_specifics_and_comments": "",
                    "equipment_quantity": 1.0,
                    "references": ""
                },
                {
                    "equipment_type": "Apparatus Earthquake simulator",
                    "equipment_group": "MODEXSIS",
                    "equipment_name": "3D Strike-slip earthquake simulator",
                    "equipment_brand": "Lab-made prototype",
                    "equipment_contact_person": "Stephane DOMINGUEZ",
                    "email_equipment_contact_person": "stephane.dominguez@gm.univ-montp2.fr",
                    "equipment_website": "GMmodel - CNRS-Montpellier University, France",
                    "equipment_specifics_and_comments": "",
                    "equipment_quantity": 1.0,
                    "references": ""
                },
                {
                    "equipment_type": "Apparatus Earthquake simulator",
                    "equipment_group": "SUBQUAKEX-2D",
                    "equipment_name": "2D Subduction earthquake simulator",
                    "equipment_brand": "Lab-made prototype",
                    "equipment_contact_person": "Stephane DOMINGUEZ",
                    "email_equipment_contact_person": "stephane.dominguez@gm.univ-montp2.fr",
                    "equipment_website": "GMmodel - CNRS-Montpellier University, France",
                    "equipment_specifics_and_comments": "",
                    "equipment_quantity": 1.0,
                    "references": ""
                },
                {
                    "equipment_type": "Apparatus Earthquake simulator",
                    "equipment_group": "SUBQUAKEX-3D",
                    "equipment_name": "3D Subduction earthquake simulator",
                    "equipment_brand": "Lab-made prototype",
                    "equipment_contact_person": "Stephane DOMINGUEZ",
                    "email_equipment_contact_person": "stephane.dominguez@gm.univ-montp2.fr",
                    "equipment_website": "GMmodel - CNRS-Montpellier University, France",
                    "equipment_specifics_and_comments": "",
                    "equipment_quantity": 1.0,
                    "references": ""
                },
                {
                    "equipment_type": "Apparatus Wedge simulator ",
                    "equipment_group": "SUB2D",
                    "equipment_name": "2D subduction accretionary wedge simulator",
                    "equipment_brand": "Lab-made prototype",
                    "equipment_contact_person": "Stephane DOMINGUEZ",
                    "email_equipment_contact_person": "stephane.dominguez@gm.univ-montp2.fr",
                    "equipment_website": "GMmodel - CNRS-Montpellier University, France",
                    "equipment_specifics_and_comments": "",
                    "equipment_quantity": 1.0,
                    "references": ""
                },
                {
                    "equipment_type": "Apparatus Wedge simulator",
                    "equipment_group": "PRISM2D",
                    "equipment_name": "2D orogenic prism simulator",
                    "equipment_brand": "Lab-made prototype",
                    "equipment_contact_person": "Stephane DOMINGUEZ",
                    "email_equipment_contact_person": "stephane.dominguez@gm.univ-montp2.fr",
                    "equipment_website": "GMmodel - CNRS-Montpellier University, France",
                    "equipment_specifics_and_comments": "",
                    "equipment_quantity": 1.0,
                    "references": ""
                },
                {
                    "equipment_type": "Monitoring Laser interferometer",
                    "equipment_group": "PORTmax",
                    "equipment_name": "Large ??????",
                    "equipment_brand": "Lab-made prototype",
                    "equipment_contact_person": "Stephane DOMINGUEZ",
                    "email_equipment_contact_person": "stephane.dominguez@gm.univ-montp2.fr",
                    "equipment_website": "GMmodel - CNRS-Montpellier University, France",
                    "equipment_specifics_and_comments": "",
                    "equipment_quantity": 1.0,
                    "references": ""
                },
                {
                    "equipment_type": "Apparatus Sandbox > Sandbox (meter scale)",
                    "equipment_group": "PRISM3Dmax",
                    "equipment_name": "Large 3D Deformation table",
                    "equipment_brand": "Lab-made prototype",
                    "equipment_contact_person": "Stephane DOMINGUEZ",
                    "email_equipment_contact_person": "stephane.dominguez@gm.univ-montp2.fr",
                    "equipment_website": "GMmodel - CNRS-Montpellier University, France",
                    "equipment_specifics_and_comments": "",
                    "equipment_quantity": 1.0,
                    "references": ""
                },
                {
                    "equipment_type": "Apparatus Fluid injector",
                    "equipment_group": "MAGINTRUSION",
                    "equipment_name": "Magmatic intrusion simulator",
                    "equipment_brand": "Lab-made prototype",
                    "equipment_contact_person": "Stephane DOMINGUEZ",
                    "email_equipment_contact_person": "stephane.dominguez@gm.univ-montp2.fr",
                    "equipment_website": "GMmodel - CNRS-Montpellier University, France",
                    "equipment_specifics_and_comments": "",
                    "equipment_quantity": 1.0,
                    "references": ""
                },
                {
                    "equipment_type": "Apparatus Fluid injector",
                    "equipment_group": "VOLCANOMAKER",
                    "equipment_name": "Volcano simulator",
                    "equipment_brand": "Lab-made prototype",
                    "equipment_contact_person": "Stephane DOMINGUEZ",
                    "email_equipment_contact_person": "stephane.dominguez@gm.univ-montp2.fr",
                    "equipment_website": "GMmodel - CNRS-Montpellier University, France",
                    "equipment_specifics_and_comments": "",
                    "equipment_quantity": 1.0,
                    "references": ""
                },
                {
                    "equipment_type": "Apparatus Sandbox > Sandbox (meter scale)",
                    "equipment_group": "PRISM3D",
                    "equipment_name": "Medium 3D deformation tabl",
                    "equipment_brand": "Lab-made prototype",
                    "equipment_contact_person": "Stephane DOMINGUEZ",
                    "email_equipment_contact_person": "stephane.dominguez@gm.univ-montp2.fr",
                    "equipment_website": "GMmodel - CNRS-Montpellier University, France",
                    "equipment_specifics_and_comments": "",
                    "equipment_quantity": 1.0,
                    "references": ""
                },
                {
                    "equipment_type": "Apparatus Fault simulator",
                    "equipment_group": "FAILLE3D",
                    "equipment_name": "3D Single Fault simulator",
                    "equipment_brand": "Lab-made prototype",
                    "equipment_contact_person": "Stephane DOMINGUEZ",
                    "email_equipment_contact_person": "stephane.dominguez@gm.univ-montp2.fr",
                    "equipment_website": "GMmodel - CNRS-Montpellier University, France",
                    "equipment_specifics_and_comments": "",
                    "equipment_quantity": 1.0,
                    "references": ""
                },
                {
                    "equipment_type": "Apparatus Tsunami simulator",
                    "equipment_group": "TSUNAMI",
                    "equipment_name": "2D subduction zone and tsunami simulator",
                    "equipment_brand": "Lab-made prototype",
                    "equipment_contact_person": "Stephane DOMINGUEZ",
                    "email_equipment_contact_person": "stephane.dominguez@gm.univ-montp2.fr",
                    "equipment_website": "GMmodel - CNRS-Montpellier University, France",
                    "equipment_specifics_and_comments": "",
                    "equipment_quantity": 1.0,
                    "references": ""
                },
                {
                    "equipment_type": "Apparatus Rainfall system",
                    "equipment_group": "BRUM1",
                    "equipment_name": "Large Rainfall system",
                    "equipment_brand": "Lab-made prototype",
                    "equipment_contact_person": "Stephane DOMINGUEZ",
                    "email_equipment_contact_person": "stephane.dominguez@gm.univ-montp2.fr",
                    "equipment_website": "GMmodel - CNRS-Montpellier University, France",
                    "equipment_specifics_and_comments": "16 sprinklers with rainfall rate controller",
                    "equipment_quantity": 1.0,
                    "references": ""
                },
                {
                    "equipment_type": "",
                    "equipment_group": "BRUM2",
                    "equipment_name": "Medium Rainfall system",
                    "equipment_brand": "Lab-made prototype",
                    "equipment_contact_person": "Stephane DOMINGUEZ",
                    "email_equipment_contact_person": "stephane.dominguez@gm.univ-montp2.fr",
                    "equipment_website": "GMmodel - CNRS-Montpellier University, France",
                    "equipment_specifics_and_comments": "8 sprinklers with rainfall rate controller",
                    "equipment_quantity": 1.0,
                    "references": ""
                },
                {
                    "equipment_type": "Apparatus 3D Convection box",
                    "equipment_group": "CONVECT3D",
                    "equipment_name": "3D Mantle convection simulator",
                    "equipment_brand": "Lab-made prototype",
                    "equipment_contact_person": "Stephane DOMINGUEZ",
                    "email_equipment_contact_person": "stephane.dominguez@gm.univ-montp2.fr",
                    "equipment_website": "GMmodel - CNRS-Montpellier University, France",
                    "equipment_specifics_and_comments": "",
                    "equipment_quantity": "",
                    "references": ""
                },
                {
                    "equipment_type": "Apparatus Hubbert-type shear box",
                    "equipment_group": "PARAMX",
                    "equipment_name": "Machine à cisaillement linéaire direct",
                    "equipment_brand": "Lab-made prototype",
                    "equipment_contact_person": "Stephane DOMINGUEZ",
                    "email_equipment_contact_person": "stephane.dominguez@gm.univ-montp2.fr",
                    "equipment_website": "GMmodel - CNRS-Montpellier University, France",
                    "equipment_specifics_and_comments": "",
                    "equipment_quantity": 1.0,
                    "references": ""
                },
                {
                    "equipment_type": "Apparatus Ring-shear tester",
                    "equipment_group": "SHEAR",
                    "equipment_name": "Machine à cisaillement annulaire",
                    "equipment_brand": "?????",
                    "equipment_contact_person": "Stephane DOMINGUEZ",
                    "email_equipment_contact_person": "stephane.dominguez@gm.univ-montp2.fr",
                    "equipment_website": "GMmodel - CNRS-Montpellier University, France",
                    "equipment_specifics_and_comments": "",
                    "equipment_quantity": 1.0,
                    "references": ""
                },
                {
                    "equipment_type": "Monitoring Photoelasticity",
                    "equipment_group": "PHOTOELAST",
                    "equipment_name": "Banc de Photoélasticimétrie",
                    "equipment_brand": "Lab-made prototype",
                    "equipment_contact_person": "Stephane DOMINGUEZ",
                    "email_equipment_contact_person": "stephane.dominguez@gm.univ-montp2.fr",
                    "equipment_website": "GMmodel - CNRS-Montpellier University, France",
                    "equipment_specifics_and_comments": "",
                    "equipment_quantity": 1.0,
                    "references": ""
                },
                {
                    "equipment_type": "Apparatus Triaxal tester",
                    "equipment_group": "TRIAX1",
                    "equipment_name": "Presse triaxiale",
                    "equipment_brand": "?????",
                    "equipment_contact_person": "Stephane DOMINGUEZ",
                    "email_equipment_contact_person": "stephane.dominguez@gm.univ-montp2.fr",
                    "equipment_website": "GMmodel - CNRS-Montpellier University, France",
                    "equipment_specifics_and_comments": "",
                    "equipment_quantity": 1.0,
                    "references": ""
                },
                {
                    "equipment_type": "Software",
                    "equipment_name": "Envi-IDL, Matlab, Photoscan (Agisoft), Visual Basic, StereoScan (Agisoft), Velocimetry (PIV) > COSI-Corr",
                    "equipment_brand": "",
                    "equipment_contact_person": "Stephane DOMINGUEZ",
                    "email_equipment_contact_person": "stephane.dominguez@gm.univ-montp2.fr",
                    "equipment_website": "GMmodel - CNRS-Montpellier University, France",
                    "equipment_specifics_and_comments": "",
                    "equipment_quantity": 1.0,
                    "references": ""
                },
                {
                    "equipment_type": "Apparatus Sandbox > Sandbox (meter scale)",
                    "equipment_group": "TECTO3D",
                    "equipment_name": "Simulateur de tectonique crustale et/ou gravitaire",
                    "equipment_brand": "Lab-made prototype",
                    "equipment_contact_person": "Bruno VENDEVILLE",
                    "email_equipment_contact_person": "Bruno.Vendeville@univ-lille1.fr ",
                    "equipment_website": "LOGmodel - CNRS-Lille 1 University, France",
                    "equipment_specifics_and_comments": "",
                    "equipment_quantity": 1.0,
                    "references": ""
                },
                {
                    "equipment_type": "Apparatus Fluid pressure device",
                    "equipment_group": "DOMALIS",
                    "equipment_name": "Pore/fluid pressure deformation simulator",
                    "equipment_brand": "Lab-made prototype",
                    "equipment_contact_person": "Bruno VENDEVILLE",
                    "email_equipment_contact_person": "Bruno.Vendeville@univ-lille1.fr ",
                    "equipment_website": "LOGmodel - CNRS-Lille 1 University, France",
                    "equipment_specifics_and_comments": "",
                    "equipment_quantity": 1.0,
                    "references": ""
                },
                {
                    "equipment_type": "Apparatus Turbidity current simulator",
                    "equipment_group": "TURBIDITOR",
                    "equipment_name": " Turbidity current simulator",
                    "equipment_brand": "Lab-made prototype",
                    "equipment_contact_person": "Bruno VENDEVILLE",
                    "email_equipment_contact_person": "Bruno.Vendeville@univ-lille1.fr ",
                    "equipment_website": "LOGmodel - CNRS-Lille 1 University, France",
                    "equipment_specifics_and_comments": "",
                    "equipment_quantity": 1.0,
                    "references": ""
                },
                {
                    "equipment_type": "Software",
                    "equipment_name": "",
                    "equipment_brand": "",
                    "equipment_contact_person": "Bruno VENDEVILLE",
                    "email_equipment_contact_person": "Bruno.Vendeville@univ-lille1.fr ",
                    "equipment_website": "LOGmodel - CNRS-Lille 1 University, France",
                    "equipment_specifics_and_comments": "",
                    "equipment_quantity": 1.0,
                    "references": ""
                },
                {
                    "equipment_type": "Apparatus Sandbox > Sandbox (meter scale)",
                    "equipment_group": "PRISM Fluid",
                    "equipment_name": "2D orogenic prism simulator with pressurized fluids",
                    "equipment_brand": "Lab-made prototype",
                    "equipment_contact_person": "Régis MOURGUES",
                    "email_equipment_contact_person": "Regis.Mourgues@univ-lemans.fr",
                    "equipment_website": "Geoϕlab - CNRS-Maine University,  France",
                    "equipment_specifics_and_comments": "",
                    "equipment_quantity": 1.0,
                    "references": ""
                },
                {
                    "equipment_type": "Apparatus Wedge simulator 2D",
                    "equipment_group": "PRISM 2D",
                    "equipment_name": "2D orogenic prism simulator",
                    "equipment_brand": "Lab-made prototype",
                    "equipment_contact_person": "Régis MOURGUES",
                    "email_equipment_contact_person": "Regis.Mourgues@univ-lemans.fr",
                    "equipment_website": "Geoϕlab - CNRS-Maine University,  France",
                    "equipment_specifics_and_comments": "",
                    "equipment_quantity": 1.0,
                    "references": ""
                },
                {
                    "equipment_type": "Apparatus Glass/Plexiglas box > Glass/Plexiglas box (cm scale)\n",
                    "equipment_group": "HydroFRACT2D",
                    "equipment_name": "2D hydrofracturation simulator in a water saturized reservoir",
                    "equipment_brand": "Lab-made prototype",
                    "equipment_contact_person": "Régis MOURGUES",
                    "email_equipment_contact_person": "Regis.Mourgues@univ-lemans.fr",
                    "equipment_website": "Geoϕlab - CNRS-Maine University,  France",
                    "equipment_specifics_and_comments": "",
                    "equipment_quantity": 1.0,
                    "references": ""
                },
                {
                    "equipment_type": "Apparatus Glass/Plexiglas box > Glass/Plexiglas box (meter scale)\n",
                    "equipment_group": "HydroFRACT3D",
                    "equipment_name": "2D hydrofracturation simulator in a water saturized reservoir",
                    "equipment_brand": "Lab-made prototype",
                    "equipment_contact_person": "Régis MOURGUES",
                    "email_equipment_contact_person": "Regis.Mourgues@univ-lemans.fr",
                    "equipment_website": "Geoϕlab - CNRS-Maine University,  France",
                    "equipment_specifics_and_comments": "",
                    "equipment_quantity": 1.0,
                    "references": ""
                },
                {
                    "equipment_type": "Apparatus Fluid injector",
                    "equipment_group": "SAND-INJECT2D",
                    "equipment_name": "Sand Intrusion simulator",
                    "equipment_brand": "Lab-made prototype",
                    "equipment_contact_person": "Régis MOURGUES",
                    "email_equipment_contact_person": "Regis.Mourgues@univ-lemans.fr",
                    "equipment_website": "Geoϕlab - CNRS-Maine University,  France",
                    "equipment_specifics_and_comments": "",
                    "equipment_quantity": 1.0,
                    "references": ""
                },
                {
                    "equipment_type": "Apparatus Fluid injector",
                    "equipment_group": "MAGMA-2D",
                    "equipment_name": "Magmatic Intrusion simulator",
                    "equipment_brand": "Lab-made prototype",
                    "equipment_contact_person": "Régis MOURGUES",
                    "email_equipment_contact_person": "Regis.Mourgues@univ-lemans.fr",
                    "equipment_website": "Geoϕlab - CNRS-Maine University,  France",
                    "equipment_specifics_and_comments": "",
                    "equipment_quantity": 1.0,
                    "references": ""
                },
                {
                    "equipment_type": "Apparatus Gravity sliding simulator",
                    "equipment_group": "LANDSLIDE-Fluid1",
                    "equipment_name": "Fluid overpressured triggered landslide simulator",
                    "equipment_brand": "Lab-made prototype",
                    "equipment_contact_person": "Régis MOURGUES",
                    "email_equipment_contact_person": "Regis.Mourgues@univ-lemans.fr",
                    "equipment_website": "Geoϕlab - CNRS-Maine University,  France",
                    "equipment_specifics_and_comments": "",
                    "equipment_quantity": 1.0,
                    "references": ""
                },
                {
                    "equipment_type": "Apparatus Gravity sliding simulator",
                    "equipment_group": "LANDSLIDE-Fluid2",
                    "equipment_name": "Etalement gravitaire de biseaux sédimentaires. Instabilités gravitaires déclenchées par de fortes pressions de fluide interstitiel",
                    "equipment_brand": "",
                    "equipment_contact_person": "Régis MOURGUES",
                    "email_equipment_contact_person": "Regis.Mourgues@univ-lemans.fr",
                    "equipment_website": "Geoϕlab - CNRS-Maine University,  France",
                    "equipment_specifics_and_comments": "",
                    "equipment_quantity": 1.0,
                    "references": ""
                },
                {
                    "equipment_type": "Apparatus Extension box",
                    "equipment_group": "HYDRO-TENSILE",
                    "equipment_name": "Perméabilité à l’air + résistance en tension des matériaux faiblement cohésifs fracturation hydraulique",
                    "equipment_brand": "",
                    "equipment_contact_person": "Régis MOURGUES",
                    "email_equipment_contact_person": "Regis.Mourgues@univ-lemans.fr",
                    "equipment_website": "Geoϕlab - CNRS-Maine University,  France",
                    "equipment_specifics_and_comments": "",
                    "equipment_quantity": 1.0,
                    "references": ""
                },
                {
                    "equipment_type": "Monitoring High frame rate camera",
                    "equipment_group": "COREL100",
                    "equipment_name": "Caméra numérique rapide + corrélation d’images pour mesure 2D des déplacements et déformations",
                    "equipment_brand": "",
                    "equipment_contact_person": "Régis MOURGUES",
                    "email_equipment_contact_person": "Regis.Mourgues@univ-lemans.fr",
                    "equipment_website": "Geoϕlab - CNRS-Maine University,  France",
                    "equipment_specifics_and_comments": "100 fp/s",
                    "equipment_quantity": 1.0,
                    "references": ""
                },
                {
                    "equipment_type": "Apparatus Hubbert-type shear box",
                    "equipment_group": "MULTI-CIS",
                    "equipment_name": "Cohésion and Friction measurements of anisotrop materials",
                    "equipment_brand": "Lab-made prototype",
                    "equipment_contact_person": "Régis MOURGUES",
                    "email_equipment_contact_person": "Regis.Mourgues@univ-lemans.fr",
                    "equipment_website": "Geoϕlab - CNRS-Maine University,  France",
                    "equipment_specifics_and_comments": "",
                    "equipment_quantity": 1.0,
                    "references": ""
                },
                {
                    "equipment_type": "Software",
                    "equipment_name": "",
                    "equipment_brand": "",
                    "equipment_contact_person": "Régis MOURGUES",
                    "email_equipment_contact_person": "Regis.Mourgues@univ-lemans.fr",
                    "equipment_website": "Geoϕlab - CNRS-Maine University,  France",
                    "equipment_specifics_and_comments": "",
                    "equipment_quantity": 1.0,
                    "references": ""
                },
                {
                    "equipment_type": "Apparatus Gravity load device (Centrifuge)",
                    "equipment_group": "GRAVI",
                    "equipment_name": "Dispositif de Chargement",
                    "equipment_brand": "Lab-made prototype",
                    "equipment_contact_person": "Stéphane BOUISSOU",
                    "email_equipment_contact_person": "bouissou@geoazur.unice.fr",
                    "equipment_website": "GEOAZURmodel - CNRS-Nice Sophia Antipolis University, France",
                    "equipment_specifics_and_comments": "Dimensions (2.5m x 1m x 1m) accelerometer 500 m.s-2",
                    "equipment_quantity": 1.0,
                    "references": ""
                },
                {
                    "equipment_type": "Apparatus Triaxal tester",
                    "equipment_group": "TRIAX1",
                    "equipment_name": "Dispositif de chargement.",
                    "equipment_brand": "?????",
                    "equipment_contact_person": "Stéphane BOUISSOU",
                    "email_equipment_contact_person": "bouissou@geoazur.unice.fr",
                    "equipment_website": "GEOAZURmodel - CNRS-Nice Sophia Antipolis University, France",
                    "equipment_specifics_and_comments": "Dimensions (2.5m x 2m x 1m) Uniaxiale 50 KN + Pressure 2 MPa",
                    "equipment_quantity": 1.0,
                    "references": ""
                },
                {
                    "equipment_type": "Apparatus Triaxal tester",
                    "equipment_group": "TRIAX2",
                    "equipment_name": "Dispositif de chargement",
                    "equipment_brand": "?????",
                    "equipment_contact_person": "Stéphane BOUISSOU",
                    "email_equipment_contact_person": "bouissou@geoazur.unice.fr",
                    "equipment_website": "GEOAZURmodel - CNRS-Nice Sophia Antipolis University, France",
                    "equipment_specifics_and_comments": "Dimensions (0.5m x 0.5m x 1m) Up to 2MPa blog 3 axis",
                    "equipment_quantity": 1.0,
                    "references": ""
                },
                {
                    "equipment_type": "Apparatus box Glass/Plexiglas box > Glass/Plexiglas box (meter scale)",
                    "equipment_group": "SUBD",
                    "equipment_name": "3D subduction, continental collision, rifting",
                    "equipment_brand": "",
                    "equipment_contact_person": "Stéphane BOUISSOU",
                    "email_equipment_contact_person": "bouissou@geoazur.unice.fr",
                    "equipment_website": "GEOAZURmodel - CNRS-Nice Sophia Antipolis University, France",
                    "equipment_specifics_and_comments": "Dimensions : (0.5m x 0.5m x 0.4m) Strength and Strain gauges",
                    "equipment_quantity": 1.0,
                    "references": ""
                },
                {
                    "equipment_type": "Apparatus Sandbox > Sandbox (meter scale)",
                    "equipment_name": "TECTO",
                    "equipment_brand": "Lab-made prototype",
                    "equipment_contact_person": "Stéphane BONNET",
                    "email_equipment_contact_person": "stephane.bonnet@get.obs-mip.fr",
                    "equipment_website": "GETmodel - CNRS-Toulouse University, France",
                    "equipment_specifics_and_comments": "Stepping motorized",
                    "equipment_quantity": 1.0,
                    "references": ""
                },
                {
                    "equipment_type": "Apparatus Fog box",
                    "equipment_group": "FOGBOX",
                    "equipment_name": "Rainfall system",
                    "equipment_brand": "Lab-made prototype",
                    "equipment_contact_person": "Stéphane BONNET",
                    "email_equipment_contact_person": "stephane.bonnet@get.obs-mip.fr",
                    "equipment_website": "GETmodel - CNRS-Toulouse University, France",
                    "equipment_specifics_and_comments": "Dimensions (1.8m x 1.8m x 2.8m) fluxmeter",
                    "equipment_quantity": 1.0,
                    "references": ""
                },
                {
                    "equipment_type": "Apparatus Sandbox > Sandbox (cm scale)",
                    "equipment_name": "SMALLBOX",
                    "equipment_brand": "Lab-made prototype",
                    "equipment_contact_person": "Bertrand MAILLOT",
                    "email_equipment_contact_person": "bertrand.maillot@u-cergy.fr",
                    "equipment_website": "GECmodel - CNRS-Cergy-Pontoise University, France ",
                    "equipment_specifics_and_comments": "Dimensions (0.3m x 0.4m x 0.04m) - Strength gauge",
                    "equipment_quantity": 1.0,
                    "references": ""
                },
                {
                    "equipment_type": "Apparatus Sandbox > Sandbox (meter scale)",
                    "equipment_name": "BIGBOX",
                    "equipment_brand": "Lab-made prototype",
                    "equipment_contact_person": "Bertrand MAILLOT",
                    "email_equipment_contact_person": "bertrand.maillot@u-cergy.fr",
                    "equipment_website": "GECmodel - CNRS-Cergy-Pontoise University, France",
                    "equipment_specifics_and_comments": "Dimensions (1.1m x 1m x 0.07m)",
                    "equipment_quantity": 1.0,
                    "references": ""
                },
                {
                    "equipment_type": "Apparatus Sieving device",
                    "equipment_name": "SMALLSEM",
                    "equipment_brand": "Lab-made prototype",
                    "equipment_contact_person": "Bertrand MAILLOT",
                    "email_equipment_contact_person": "bertrand.maillot@u-cergy.fr",
                    "equipment_website": "GECmodel - CNRS-Cergy-Pontoise University, France",
                    "equipment_specifics_and_comments": "Dimensions (0.4m x 0.4m x 1.93m)",
                    "equipment_quantity": 1.0,
                    "references": ""
                },
                {
                    "equipment_type": "Apparatus Sieving device",
                    "equipment_name": "BIGSEM",
                    "equipment_brand": "Lab-made prototype",
                    "equipment_contact_person": "Bertrand MAILLOT",
                    "email_equipment_contact_person": "bertrand.maillot@u-cergy.fr",
                    "equipment_website": "GECmodel - CNRS-Cergy-Pontoise University, France",
                    "equipment_specifics_and_comments": "Dimensions (1.3m x 1.3m x 1.93m)",
                    "equipment_quantity": 1.0,
                    "references": ""
                },
                {
                    "equipment_type": "Apparatus Hubbert-type shear box",
                    "equipment_name": "FRICSYSTEM",
                    "equipment_brand": "Lab-made prototype",
                    "equipment_contact_person": "Bertrand MAILLOT",
                    "email_equipment_contact_person": "bertrand.maillot@u-cergy.fr",
                    "equipment_website": "GECmodel - CNRS-Cergy-Pontoise University, France",
                    "equipment_specifics_and_comments": "",
                    "equipment_quantity": 1.0,
                    "references": ""
                },
                {
                    "equipment_type": "Software",
                    "equipment_name": "",
                    "equipment_brand": "",
                    "equipment_contact_person": "Bertrand MAILLOT",
                    "email_equipment_contact_person": "bertrand.maillot@u-cergy.fr",
                    "equipment_website": "GECmodel - CNRS-Cergy-Pontoise University, France",
                    "equipment_specifics_and_comments": "",
                    "equipment_quantity": 1.0,
                    "references": ""
                },
                {
                    "equipment_type": "Apparatus Rheometer",
                    "equipment_name": "ROTARHEOMETER",
                    "equipment_brand": "Anton Paar MCR 501",
                    "equipment_contact_person": "Anne DAVAILLE",
                    "email_equipment_contact_person": "davaille@fast.u-psud.fr",
                    "equipment_website": "FASTmodel - CNRS-Paris Sud Orsay University, France",
                    "equipment_specifics_and_comments": "",
                    "equipment_quantity": 1.0,
                    "references": ""
                },
                {
                    "equipment_type": "Monitoring  Thermochromic liquid crystals",
                    "equipment_group": "VISUTLC ",
                    "equipment_name": "Isotherms Visualization",
                    "equipment_brand": "?????",
                    "equipment_contact_person": "Anne DAVAILLE",
                    "email_equipment_contact_person": "davaille@fast.u-psud.fr",
                    "equipment_website": "FASTmodel - CNRS-Paris Sud Orsay University, France",
                    "equipment_specifics_and_comments": "",
                    "equipment_quantity": 1.0,
                    "references": ""
                },
                {
                    "equipment_type": "Monitoring ",
                    "equipment_group": "DFV ",
                    "equipment_name": "Diffusive Flow Velocimetry",
                    "equipment_brand": "?????",
                    "equipment_contact_person": "Anne DAVAILLE",
                    "email_equipment_contact_person": "davaille@fast.u-psud.fr",
                    "equipment_website": "FASTmodel - CNRS-Paris Sud Orsay University, France",
                    "equipment_specifics_and_comments": "",
                    "equipment_quantity": 1.0,
                    "references": ""
                },
                {
                    "equipment_type": "Apparatus Granulometer",
                    "equipment_name": "GRANULOMETER",
                    "equipment_brand": "MorphologiG3 MALVERN",
                    "equipment_contact_person": "Anne DAVAILLE",
                    "email_equipment_contact_person": "davaille@fast.u-psud.fr",
                    "equipment_website": "FASTmodel - CNRS-Paris Sud Orsay University, France",
                    "equipment_specifics_and_comments": "",
                    "equipment_quantity": 1.0,
                    "references": ""
                },
                {
                    "equipment_type": "Apparatus",
                    "equipment_name": "Electromechanical Testing Machine «INSTRON 5882»",
                    "equipment_brand": "INSTRON 5882",
                    "equipment_contact_person": "Anne DAVAILLE",
                    "email_equipment_contact_person": "davaille@fast.u-psud.fr",
                    "equipment_website": "FASTmodel - CNRS-Paris Sud Orsay University, France",
                    "equipment_specifics_and_comments": "",
                    "equipment_quantity": 1.0,
                    "references": ""
                },
                {
                    "equipment_type": "Apparatus 2D Convection box",
                    "equipment_group": "CONVECT2D",
                    "equipment_name": "2D Mantle convection simulator",
                    "equipment_brand": "Lab-made prototype",
                    "equipment_contact_person": "Anne DAVAILLE",
                    "email_equipment_contact_person": "davaille@fast.u-psud.fr",
                    "equipment_website": "FASTmodel - CNRS-Paris Sud Orsay University, France",
                    "equipment_specifics_and_comments": "",
                    "equipment_quantity": 1.0,
                    "references": ""
                },
                {
                    "equipment_type": "Apparatus 3D Convection box",
                    "equipment_group": "CONVECT3D",
                    "equipment_name": "3D Mantle convection simulator",
                    "equipment_brand": "Lab-made prototype",
                    "equipment_contact_person": "Anne DAVAILLE",
                    "email_equipment_contact_person": "davaille@fast.u-psud.fr",
                    "equipment_website": "FASTmodel - CNRS-Paris Sud Orsay University, France",
                    "equipment_specifics_and_comments": "",
                    "equipment_quantity": 1.0,
                    "references": ""
                },
                {
                    "equipment_type": "Aparatus",
                    "equipment_group": "PROFILOMETER",
                    "equipment_name": "2D profiling or 3D cartography of solid surfaces",
                    "equipment_brand": "Bruker - DEKTAKXT",
                    "equipment_contact_person": "Anne DAVAILLE",
                    "email_equipment_contact_person": "davaille@fast.u-psud.fr",
                    "equipment_website": "FASTmodel - CNRS-Paris Sud Orsay University, France",
                    "equipment_specifics_and_comments": "",
                    "equipment_quantity": 1.0,
                    "references": ""
                },
                {
                    "equipment_type": "Apparatus Densimeter",
                    "equipment_name": "DENSIMETER",
                    "equipment_brand": "",
                    "equipment_contact_person": "Anne DAVAILLE",
                    "email_equipment_contact_person": "davaille@fast.u-psud.fr",
                    "equipment_website": "FASTmodel - CNRS-Paris Sud Orsay University, France",
                    "equipment_specifics_and_comments": "",
                    "equipment_quantity": "",
                    "references": ""
                },
                {
                    "equipment_type": "Software",
                    "equipment_name": "Labview software",
                    "equipment_brand": "",
                    "equipment_contact_person": "Anne DAVAILLE",
                    "email_equipment_contact_person": "davaille@fast.u-psud.fr",
                    "equipment_website": "FASTmodel - CNRS-Paris Sud Orsay University, France",
                    "equipment_specifics_and_comments": "",
                    "equipment_quantity": 1.0,
                    "references": ""
                },
                {
                    "equipment_type": "Apparatus Granular flow simulator",
                    "equipment_group": "EGRAFLU",
                    "equipment_name": "Experimental channel for fluidized granular flows",
                    "equipment_brand": "Lab-made prototype",
                    "equipment_contact_person": "Olivier ROCHE",
                    "email_equipment_contact_person": "O.Roche@opgc.univ-bpclermont.fr",
                    "equipment_website": "LMVmodel - CNRS-Clermont-Ferrand University, France",
                    "equipment_specifics_and_comments": "",
                    "equipment_quantity": 1.0,
                    "references": ""
                },
                {
                    "equipment_type": "Apparatus Granular flow simulator",
                    "equipment_group": "EGRA",
                    "equipment_name": "Experimental channel for continuous granular flows",
                    "equipment_brand": "Lab-made prototype",
                    "equipment_contact_person": "Olivier ROCHE",
                    "email_equipment_contact_person": "O.Roche@opgc.univ-bpclermont.fr",
                    "equipment_website": "LMVmodel - CNRS-Clermont-Ferrand University, France",
                    "equipment_specifics_and_comments": "",
                    "equipment_quantity": 1.0,
                    "references": ""
                },
                {
                    "equipment_type": "Apparatus Fluid injector",
                    "equipment_group": "INTRUMAG",
                    "equipment_name": "Magmatic intrusion simulator",
                    "equipment_brand": "Lab-made prototype",
                    "equipment_contact_person": "Olivier ROCHE",
                    "email_equipment_contact_person": "O.Roche@opgc.univ-bpclermont.fr",
                    "equipment_website": "LMVmodel - CNRS-Clermont-Ferrand University, France",
                    "equipment_specifics_and_comments": "",
                    "equipment_quantity": 1.0,
                    "references": ""
                },
                {
                    "equipment_type": "Apparatus Fluid injector termally controlled",
                    "equipment_group": "BM",
                    "equipment_name": "Fluid injector under controled temperature",
                    "equipment_brand": "",
                    "equipment_contact_person": "Olivier ROCHE",
                    "email_equipment_contact_person": "O.Roche@opgc.univ-bpclermont.fr",
                    "equipment_website": "LMVmodel - CNRS-Clermont-Ferrand University, France",
                    "equipment_specifics_and_comments": "",
                    "equipment_quantity": 1.0,
                    "references": ""
                },
                {
                    "equipment_type": "Apparatus Peristaltic pump",
                    "equipment_group": "PERISPUMP",
                    "equipment_name": "Peristaltic pump",
                    "equipment_brand": "Watson Marlow série 520S",
                    "equipment_contact_person": "Olivier ROCHE",
                    "email_equipment_contact_person": "O.Roche@opgc.univ-bpclermont.fr",
                    "equipment_website": "LMVmodel - CNRS-Clermont-Ferrand University, France",
                    "equipment_specifics_and_comments": "",
                    "equipment_quantity": 1.0,
                    "references": ""
                },
                {
                    "equipment_type": "Apparatus Heating device",
                    "equipment_group": "CHAUFIND",
                    "equipment_name": "Industrial water heater",
                    "equipment_brand": "?????",
                    "equipment_contact_person": "Olivier ROCHE",
                    "email_equipment_contact_person": "O.Roche@opgc.univ-bpclermont.fr",
                    "equipment_website": "LMVmodel - CNRS-Clermont-Ferrand University, France",
                    "equipment_specifics_and_comments": "",
                    "equipment_quantity": 1.0,
                    "references": ""
                },
                {
                    "equipment_type": "Apparatus Cooler device",
                    "equipment_group": "REFRIGIND",
                    "equipment_name": "Industrial refrigerator",
                    "equipment_brand": "?????",
                    "equipment_contact_person": "Olivier ROCHE",
                    "email_equipment_contact_person": "O.Roche@opgc.univ-bpclermont.fr",
                    "equipment_website": "LMVmodel - CNRS-Clermont-Ferrand University, France",
                    "equipment_specifics_and_comments": "",
                    "equipment_quantity": 1.0,
                    "references": ""
                },
                {
                    "equipment_type": "Software",
                    "equipment_name": "Photoscan",
                    "equipment_brand": "",
                    "equipment_contact_person": "Olivier ROCHE",
                    "email_equipment_contact_person": "O.Roche@opgc.univ-bpclermont.fr",
                    "equipment_website": "LMVmodel - CNRS-Clermont-Ferrand University, France",
                    "equipment_specifics_and_comments": "",
                    "equipment_quantity": 1.0,
                    "references": ""
                }
            ],
            "material": [
                {
                    "material_group": "Foam rubber",
                    "material": "Young modulus 100KPa",
                    "material_brand": "Bultex ",
                    "material_specifics_and_comments": "Young modulus 100KPa",
                    "references": "relevant papers referring to the material"
                },
                {
                    "material_group": "Gelatine > Xantan",
                    "material": "Agar-Agar gelose",
                    "material_brand": "Jaipur",
                    "material_specifics_and_comments": "Agar-Agar gelose",
                    "references": ""
                },
                {
                    "material_group": "Glass fragments",
                    "material": "Granulometry 0-50 microns",
                    "material_brand": "Sifraco",
                    "material_specifics_and_comments": "Granulometry 0-50 microns",
                    "references": ""
                },
                {
                    "material_group": "Glycerine",
                    "material": "density 1.3",
                    "material_brand": "Subolab",
                    "material_specifics_and_comments": "density 1.3",
                    "references": ""
                },
                {
                    "material_group": "Golden syrup",
                    "material": "density 1.5",
                    "material_brand": "Butiforce",
                    "material_specifics_and_comments": "density 1.5",
                    "references": ""
                },
                {
                    "material_group": "Graphite",
                    "material": "Granulometry 0-40 microns",
                    "material_brand": "Carbone Savoie",
                    "material_specifics_and_comments": "Granulometry 0-40 microns",
                    "references": ""
                },
                {
                    "material_group": "Microspheres",
                    "material": "Granulometry 0-50 microns, Granulometry 70-150 microns, Granulometry 100-200 microns",
                    "material_brand": "Fillite ",
                    "material_specifics_and_comments": "Granulometry 0-50 microns, Granulometry 70-150 microns, Granulometry 100-200 microns",
                    "references": ""
                },
                {
                    "material_group": "Microspheres > Siliceus",
                    "material": "Granulometry 100-200 microns",
                    "material_brand": "Eyraud",
                    "material_specifics_and_comments": "Granulometry 100-200 microns",
                    "references": ""
                },
                {
                    "material_group": "Paraffin",
                    "material": "density 0.9",
                    "material_brand": "Carbamex",
                    "material_specifics_and_comments": "density 0.9",
                    "references": ""
                },
                {
                    "material_group": "Plasticine",
                    "material": "Granulometry 15 microns, density 1.6-1.7",
                    "material_brand": "Herbig",
                    "material_specifics_and_comments": "Granulometry 15 microns, density 1.6-1.7",
                    "references": ""
                },
                {
                    "material_group": "Rubber",
                    "material": "Granulometry 0.5-1.5mm",
                    "material_brand": "VS rubber",
                    "material_specifics_and_comments": "Granulometry 0.5-1.5mm",
                    "references": ""
                },
                {
                    "material_group": "Sand",
                    "material": "HN38",
                    "material_brand": "Eyraud",
                    "material_specifics_and_comments": "Granulometry 100-300 microns",
                    "references": ""
                },
                {
                    "material_group": "Sand > Corundum Sand",
                    "material": "Granulometry 200-500 microns",
                    "material_brand": "Eyraud",
                    "material_specifics_and_comments": "Granulometry 200-500 microns",
                    "references": ""
                },
                {
                    "material_group": "PVC powder",
                    "material": "266SF",
                    "material_brand": "Solvay",
                    "material_specifics_and_comments": "Granulometry 30-90 microns",
                    "references": ""
                },
                {
                    "material_group": "Silicon/Silly putty/PDMS",
                    "material": "SGM36, Silbione 70009",
                    "material_brand": "Rhône-Poulenc",
                    "material_specifics_and_comments": "SGM36, Silbione 70009",
                    "references": ""
                },
                {
                    "material_group": "Anthracite",
                    "material": "Granulometry 0.5-1.5mm",
                    "material_brand": "Eyraud",
                    "material_specifics_and_comments": "Granulometry 0.5-1.5mm",
                    "references": ""
                },
                {
                    "material_group": "Calcium carbonate powder",
                    "material": "Granulometry 0-50 microns",
                    "material_brand": "Marmosoft",
                    "material_specifics_and_comments": "Granulometry 0-50 microns",
                    "references": ""
                }
            ],
            "measured_property": [
                {
                    "measured_property_group": "Bulk modulus",
                    "measured_property": "Lab-made measurement device",
                    "measured_property_specifics_and_comments": "",
                    "references": "relevant papers referring to measured property"
                },
                {
                    "measured_property_group": "Cohesion",
                    "measured_property": "Lab-made measurement device",
                    "measured_property_specifics_and_comments": "Hubert type shear box measurements",
                    "references": ""
                },
                {
                    "measured_property": "Density",
                    "measured_property_specifics_and_comments": "",
                    "references": ""
                },
                {
                    "measured_property_group": "Friction coefficient",
                    "measured_property": "Lab-made measurement device",
                    "measured_property_specifics_and_comments": "Hubert type shear box measurements",
                    "references": ""
                },
                {
                    "measured_property": "Grain size distribution",
                    "measured_property_specifics_and_comments": "Laser granulometer",
                    "references": ""
                },
                {
                    "measured_property": "Lame constant",
                    "measured_property_specifics_and_comments": "",
                    "references": ""
                },
                {
                    "measured_property": "Loss modulus",
                    "measured_property_specifics_and_comments": "",
                    "references": ""
                },
                {
                    "measured_property": "Maxwell relaxation time",
                    "measured_property_specifics_and_comments": "",
                    "references": ""
                },
                {
                    "measured_property_group": "Poisson ratio",
                    "measured_property": "Lab-made measurement device",
                    "measured_property_specifics_and_comments": "",
                    "references": ""
                },
                {
                    "measured_property": "P-wave velocity",
                    "measured_property_specifics_and_comments": "",
                    "references": ""
                },
                {
                    "measured_property": "Rate-state parameters",
                    "measured_property_specifics_and_comments": "",
                    "references": ""
                },
                {
                    "measured_property_group": "Shear modulus",
                    "measured_property": "Lab-made measurement device",
                    "measured_property_specifics_and_comments": "",
                    "references": ""
                },
                {
                    "measured_property": "Surface image",
                    "measured_property_specifics_and_comments": "",
                    "references": ""
                },
                {
                    "measured_property": "S-wave velocity",
                    "measured_property_specifics_and_comments": "",
                    "references": ""
                },
                {
                    "measured_property": "Tensile strength",
                    "measured_property_specifics_and_comments": "",
                    "references": ""
                },
                {
                    "measured_property": "Viscosity",
                    "measured_property_specifics_and_comments": "Brookfield Viscosimeter DV2",
                    "references": ""
                },
                {
                    "measured_property": "Yield stress",
                    "measured_property_specifics_and_comments": "",
                    "references": ""
                },
                {
                    "measured_property_group": "Young modulus",
                    "measured_property": "Lab-made measurement device",
                    "measured_property_specifics_and_comments": "",
                    "references": ""
                }
            ]
        },
        "data_services": [
            {
                "service_type": "data_publications_access",
                "link_label": "Go to data publications from this lab (MSL TCS catalogue portal)",
                "URL": "https://epos-msl.uu.nl/organization/f780441f60a30a86b752e00adb66f107"
            },
            {
                "service_type": "data_publications_get",
                "link_label": "Retrieve data publications from this lab",
                "URL": "https://epos-msl.uu.nl/ics/api.php?Labf780441f60a30a86b752e00adb66f107",
                "payload": "json"
            }
        ]
    }
}